AUTHORS
CHANGES
LICENSE
MANIFEST.in
README.md
requirements.txt
setup.py
fspyrpc.egg-info/PKG-INFO
fspyrpc.egg-info/SOURCES.txt
fspyrpc.egg-info/dependency_links.txt
fspyrpc.egg-info/not-zip-safe
fspyrpc.egg-info/top_level.txt
pyrpc/__init__.py
pyrpc/client.py
pyrpc/message.py
pyrpc/rpc.py
pyrpc/server.py