Metadata-Version: 1.1
Name: fspyrpc
Version: 0.0.1
Summary: A simple RPC-framework written in Python
Home-page: https://bitbucket.org/flosch/pyrpc
Author: Florian Schlachter
Author-email: flori@n-schlachter.de
License: UNKNOWN
Platform: UNKNOWN
Classifier: Development Status :: 3 - Alpha
Classifier: Intended Audience :: Developers
Classifier: License :: OSI Approved :: MIT License
Classifier: Operating System :: OS Independent
Classifier: Programming Language :: Python
